eternal/__init__.py
eternal/airc.py
eternal/libirc.py
eternal/main.py
eternal/ui.py
eternal/version.py
eternal-0.0.1.dist-info/LICENSE
eternal-0.0.1.dist-info/METADATA
eternal-0.0.1.dist-info/WHEEL
eternal-0.0.1.dist-info/entry_points.txt
eternal-0.0.1.dist-info/top_level.txt
eternal-0.0.1.dist-info/RECORD
